sonar_code_diff/__init__.py
sonar_code_diff/cli.py
sonar_code_diff-0.5.0.dist-info/LICENSE
sonar_code_diff-0.5.0.dist-info/METADATA
sonar_code_diff-0.5.0.dist-info/WHEEL
sonar_code_diff-0.5.0.dist-info/entry_points.txt
sonar_code_diff-0.5.0.dist-info/top_level.txt
sonar_code_diff-0.5.0.dist-info/RECORD
