Metadata-Version: 2.1
Name: sonar-code-diff
Version: 0.5.0
Summary: Sonar Code Diff is used to run a diff between a test code base and known code base
Home-page: https://gitlab.com/iokatech/public/sonar_code_diff
Author: Steve Graham
Author-email: steve@ioka.tech
License: MIT license
Keywords: sonar_code_diff
Platform: UNKNOWN
Classifier: Development Status :: 2 - Pre-Alpha
Classifier: Intended Audience :: Developers
Classifier: License :: OSI Approved :: MIT License
Classifier: Natural Language :: English
Classifier: Programming Language :: Python :: 3
Classifier: Programming Language :: Python :: 3.6
Classifier: Programming Language :: Python :: 3.7
Classifier: Programming Language :: Python :: 3.8
Requires-Python: >=3.6
License-File: LICENSE
Requires-Dist: Click (>=7.0)
